lancedb_tables/__init__.py
lancedb_tables/lance_table.py
lancedb_tables-0.1.3.dist-info/METADATA
lancedb_tables-0.1.3.dist-info/WHEEL
lancedb_tables-0.1.3.dist-info/RECORD
