Metadata-Version: 2.3
Name: lancedb-tables
Version: 0.1.3
Summary: An embedded streaming OLAP data pipeline with LanceDB
Author-email: Evan K <ekcopersonal@gmail.com>
Requires-Python: >=3.12
Requires-Dist: lancedb>=0.11
